<qti-assessment-item
    xmlns="http://www.imsglobal.org/xsd/imsqtiasi_v3p0"
    xmlns:xsi="http://www.w3.org/2001/XMLSchema-instance"
    xsi:schemaLocation="http://www.imsglobal.org/xsd/imsqtiasi_v3p0
      https://purl.imsglobal.org/spec/qti/v3p0/schema/xsd/imsqti_asiv3p0_v1p0.xsd"
    identifier="A-M1-ALG-01-02_Q30"
    title="Cálculo de volumen de agua en estanques"
    adaptive="false"
    time-dependent="false">
  <qti-response-declaration identifier="RESPONSE" cardinality="single" base-type="identifier">
    <qti-correct-response>
      <qti-value>A</qti-value>
    </qti-correct-response>
  </qti-response-declaration>
  <qti-outcome-declaration identifier="FEEDBACK" cardinality="single" base-type="identifier"/>
  <qti-outcome-declaration identifier="SOLUTION" cardinality="single" base-type="identifier"/>
  <qti-outcome-declaration identifier="SCORE" cardinality="single" base-type="float">
    <qti-default-value>
      <qti-value>0</qti-value>
    </qti-default-value>
  </qti-outcome-declaration>
  <qti-item-body>
    <p>En una planta de tratamiento, cada estanque de agua contiene 75 litros cuando está lleno. Se llenan 64 estanques y luego se extraen 950 litros para realizar pruebas de calidad.</p>
    <p>El volumen total de agua que queda en los estanques, en litros, se puede calcular con la expresión
      <math xmlns="http://www.w3.org/1998/Math/MathML">
        <mrow>
          <mi>x</mi>
          <mo>&#x00B7;</mo>
          <mi>y</mi>
          <mo>-</mo>
          <mi>z</mi>
        </mrow>
      </math>,
      donde
      <math xmlns="http://www.w3.org/1998/Math/MathML">
        <mrow>
          <mi>x</mi>
        </mrow>
      </math>
      es la cantidad de litros por estanque,
      <math xmlns="http://www.w3.org/1998/Math/MathML">
        <mrow>
          <mi>y</mi>
        </mrow>
      </math>
      es el número de estanques llenos y
      <math xmlns="http://www.w3.org/1998/Math/MathML">
        <mrow>
          <mi>z</mi>
        </mrow>
      </math>
      es la cantidad de litros extraídos.</p>
    <p>¿Cuál es el valor de la expresión cuando
      <math xmlns="http://www.w3.org/1998/Math/MathML">
        <mrow>
          <mi>x</mi>
          <mo>=</mo>
          <mn>75</mn>
        </mrow>
      </math>,
      <math xmlns="http://www.w3.org/1998/Math/MathML">
        <mrow>
          <mi>y</mi>
          <mo>=</mo>
          <mn>64</mn>
        </mrow>
      </math>
      y
      <math xmlns="http://www.w3.org/1998/Math/MathML">
        <mrow>
          <mi>z</mi>
          <mo>=</mo>
          <mn>950</mn>
        </mrow>
      </math>?</p>
    <qti-choice-interaction max-choices="1" response-identifier="RESPONSE">
      <qti-simple-choice identifier="A">3 850 litros.
        <qti-feedback-inline identifier="FB_A" outcome-identifier="FEEDBACK">¡Correcto! Al sustituir en la expresión
          <math xmlns="http://www.w3.org/1998/Math/MathML">
            <mi>x</mi><mo>&#x00B7;</mo><mi>y</mi><mo>-</mo><mi>z</mi>
          </math>
          los valores
          <math xmlns="http://www.w3.org/1998/Math/MathML">
            <mi>x</mi><mo>=</mo><mn>75</mn>
          </math>,
          <math xmlns="http://www.w3.org/1998/Math/MathML">
            <mi>y</mi><mo>=</mo><mn>64</mn>
          </math>
          y
          <math xmlns="http://www.w3.org/1998/Math/MathML">
            <mi>z</mi><mo>=</mo><mn>950</mn>
          </math>,
          se obtiene primero el volumen total inicial:
          <math xmlns="http://www.w3.org/1998/Math/MathML">
            <mn>75</mn><mo>&#x00B7;</mo><mn>64</mn><mo>=</mo><mn>4.800</mn>
          </math>
          litros. Luego se restan los litros extraídos:
          <math xmlns="http://www.w3.org/1998/Math/MathML">
            <mn>4.800</mn><mo>-</mo><mn>950</mn><mo>=</mo><mn>3.850</mn>
          </math>
          litros. Por lo tanto, el valor correcto de la expresión es 3.850 litros, que corresponde a esta alternativa.</qti-feedback-inline>
      </qti-simple-choice>
      <qti-simple-choice identifier="B">4 800 litros.
        <qti-feedback-inline identifier="FB_B" outcome-identifier="FEEDBACK">Incorrecto. El valor
          <math xmlns="http://www.w3.org/1998/Math/MathML">
            <mn>4.800</mn>
          </math>
          litros corresponde solo al volumen total de los estanques llenos, sin considerar la extracción. Al calcular
          <math xmlns="http://www.w3.org/1998/Math/MathML">
            <mi>x</mi><mo>&#x00B7;</mo><mi>y</mi>
          </math>
          se obtiene:
          <math xmlns="http://www.w3.org/1998/Math/MathML">
            <mn>75</mn><mo>&#x00B7;</mo><mn>64</mn><mo>=</mo><mn>4.800</mn>
          </math>
          litros. Luego, la expresión completa
          <math xmlns="http://www.w3.org/1998/Math/MathML">
            <mi>x</mi><mo>&#x00B7;</mo><mi>y</mi><mo>-</mo><mi>z</mi>
          </math>
          exige restar los 950 litros extraídos:
          <math xmlns="http://www.w3.org/1998/Math/MathML">
            <mn>4.800</mn><mo>-</mo><mn>950</mn><mo>=</mo><mn>3.850</mn>
          </math>
          litros. Por eso, 4.800 litros no es el valor correcto de la expresión.</qti-feedback-inline>
      </qti-simple-choice>
      <qti-simple-choice identifier="C">5 750 litros.
        <qti-feedback-inline identifier="FB_C" outcome-identifier="FEEDBACK">Incorrecto. El valor
          <math xmlns="http://www.w3.org/1998/Math/MathML">
            <mn>5.750</mn>
          </math>
          litros se obtiene si, en lugar de restar, se suman los litros extraídos al volumen inicial. Si se calcula primero
          <math xmlns="http://www.w3.org/1998/Math/MathML">
            <mi>x</mi><mo>&#x00B7;</mo><mi>y</mi>
          </math>,
          resulta:
          <math xmlns="http://www.w3.org/1998/Math/MathML">
            <mn>75</mn><mo>&#x00B7;</mo><mn>64</mn><mo>=</mo><mn>4.800</mn>
          </math>
          litros. Si se suman los 950 litros extraídos, se obtiene:
          <math xmlns="http://www.w3.org/1998/Math/MathML">
            <mn>4.800</mn><mo>+</mo><mn>950</mn><mo>=</mo><mn>5.750</mn>
          </math>
          litros, pero la expresión dada es una resta,
          <math xmlns="http://www.w3.org/1998/Math/MathML">
            <mi>x</mi><mo>&#x00B7;</mo><mi>y</mi><mo>-</mo><mi>z</mi>
          </math>,
          y su valor correcto es
          <math xmlns="http://www.w3.org/1998/Math/MathML">
            <mn>4.800</mn><mo>-</mo><mn>950</mn><mo>=</mo><mn>3.850</mn>
          </math>
          litros.</qti-feedback-inline>
      </qti-simple-choice>
      <qti-simple-choice identifier="D">3 750 litros.
        <qti-feedback-inline identifier="FB_D" outcome-identifier="FEEDBACK">Incorrecto. Al calcular la expresión con los valores dados, el resultado no es 3.750 litros. Primero se obtiene el volumen inicial:
          <math xmlns="http://www.w3.org/1998/Math/MathML">
            <mn>75</mn><mo>&#x00B7;</mo><mn>64</mn><mo>=</mo><mn>4.800</mn>
          </math>
          litros. Luego se deben restar los 950 litros extraídos:
          <math xmlns="http://www.w3.org/1998/Math/MathML">
            <mn>4.800</mn><mo>-</mo><mn>950</mn><mo>=</mo><mn>3.850</mn>
          </math>
          litros. Por lo tanto, 3.750 litros no coincide con el valor correcto de la expresión, que es 3.850 litros.</qti-feedback-inline>
      </qti-simple-choice>
    </qti-choice-interaction>
    <qti-feedback-block identifier="show" outcome-identifier="SOLUTION" show-hide="show">
      <qti-content-body>
        <p><strong>Resolución paso a paso de la expresión</strong></p>
        <ol>
          <li>
            <p><strong>Paso 1: Identificar la expresión y los valores</strong></p>
            <p>La expresión que representa el volumen de agua que queda en los estanques es
              <math xmlns="http://www.w3.org/1998/Math/MathML">
                <mi>x</mi><mo>&#x00B7;</mo><mi>y</mi><mo>-</mo><mi>z</mi>
              </math>, donde:
            </p>
            <p>
              <math xmlns="http://www.w3.org/1998/Math/MathML">
                <mi>x</mi><mo>=</mo><mn>75</mn>
              </math>
              representa los litros por estanque,
              <math xmlns="http://www.w3.org/1998/Math/MathML">
                <mi>y</mi><mo>=</mo><mn>64</mn>
              </math>
              representa la cantidad de estanques llenos y
              <math xmlns="http://www.w3.org/1998/Math/MathML">
                <mi>z</mi><mo>=</mo><mn>950</mn>
              </math>
              representa los litros extraídos.
            </p>
          </li>
          <li>
            <p><strong>Paso 2: Calcular el volumen total inicial</strong></p>
            <p>El volumen de agua cuando todos los estanques están llenos se obtiene multiplicando los litros por estanque por la cantidad de estanques:</p>
            <p>
              <math xmlns="http://www.w3.org/1998/Math/MathML">
                <mrow>
                  <mi>x</mi><mo>&#x00B7;</mo><mi>y</mi><mo>=</mo><mn>75</mn><mo>&#x00B7;</mo><mn>64</mn>
                </mrow>
              </math>
            </p>
            <p>Se puede descomponer el cálculo así:</p>
            <p>
              <math xmlns="http://www.w3.org/1998/Math/MathML">
                <mn>75</mn><mo>&#x00B7;</mo><mn>64</mn><mo>=</mo><mn>75</mn><mo>&#x00B7;</mo><mo>(</mo><mn>8</mn><mo>&#x00B7;</mo><mn>8</mn><mo>)</mo><mo>=</mo><mo>(</mo><mn>75</mn><mo>&#x00B7;</mo><mn>8</mn><mo>)</mo><mo>&#x00B7;</mo><mn>8</mn>
              </math>
            </p>
            <p>
              Primero:
              <math xmlns="http://www.w3.org/1998/Math/MathML">
                <mn>75</mn><mo>&#x00B7;</mo><mn>8</mn><mo>=</mo><mn>600</mn>
              </math>,
              luego:
              <math xmlns="http://www.w3.org/1998/Math/MathML">
                <mn>600</mn><mo>&#x00B7;</mo><mn>8</mn><mo>=</mo><mn>4.800</mn>
              </math>.
            </p>
            <p>Por lo tanto, el volumen inicial es de 4.800 litros.</p>
          </li>
          <li>
            <p><strong>Paso 3: Restar los litros extraídos</strong></p>
            <p>Ahora se aplican los litros extraídos usando la parte
              <math xmlns="http://www.w3.org/1998/Math/MathML">
                <mo>-</mo><mi>z</mi>
              </math>
              de la expresión:
            </p>
            <p>
              <math xmlns="http://www.w3.org/1998/Math/MathML">
                <mrow>
                  <mi>x</mi><mo>&#x00B7;</mo><mi>y</mi><mo>-</mo><mi>z</mi><mo>=</mo><mn>4.800</mn><mo>-</mo><mn>950</mn>
                </mrow>
              </math>
            </p>
            <p>Calculamos la resta paso a paso:</p>
            <p>
              <math xmlns="http://www.w3.org/1998/Math/MathML">
                <mn>4.800</mn><mo>-</mo><mn>900</mn><mo>=</mo><mn>3.900</mn>
              </math>
              y luego restamos los 50 litros que faltan:
              <math xmlns="http://www.w3.org/1998/Math/MathML">
                <mn>3.900</mn><mo>-</mo><mn>50</mn><mo>=</mo><mn>3.850</mn>
              </math>.
            </p>
            <p>Así, después de extraer 950 litros, quedan 3.850 litros en los estanques.</p>
          </li>
          <li>
            <p><strong>Paso 4: Seleccionar la alternativa correcta</strong></p>
            <p>El valor de la expresión
              <math xmlns="http://www.w3.org/1998/Math/MathML">
                <mi>x</mi><mo>&#x00B7;</mo><mi>y</mi><mo>-</mo><mi>z</mi>
              </math>
              para
              <math xmlns="http://www.w3.org/1998/Math/MathML">
                <mi>x</mi><mo>=</mo><mn>75</mn>
              </math>,
              <math xmlns="http://www.w3.org/1998/Math/MathML">
                <mi>y</mi><mo>=</mo><mn>64</mn>
              </math>
              y
              <math xmlns="http://www.w3.org/1998/Math/MathML">
                <mi>z</mi><mo>=</mo><mn>950</mn>
              </math>
              es 3.850 litros, por lo que la alternativa correcta es "3 850 litros." (alternativa A).
            </p>
          </li>
        </ol>
      </qti-content-body>
    </qti-feedback-block>
  </qti-item-body>
  <qti-response-processing>
    <qti-response-condition>
      <qti-response-if>
        <qti-match>
          <qti-variable identifier="RESPONSE"/>
          <qti-base-value base-type="identifier">A</qti-base-value>
        </qti-match>
        <qti-set-outcome-value identifier="SCORE">
          <qti-base-value base-type="float">1</qti-base-value>
        </qti-set-outcome-value>
        <qti-set-outcome-value identifier="FEEDBACK">
          <qti-base-value base-type="identifier">FB_A</qti-base-value>
        </qti-set-outcome-value>
        <qti-set-outcome-value identifier="SOLUTION">
          <qti-base-value base-type="identifier">show</qti-base-value>
        </qti-set-outcome-value>
      </qti-response-if>
      <qti-response-else-if>
        <qti-match>
          <qti-variable identifier="RESPONSE"/>
          <qti-base-value base-type="identifier">B</qti-base-value>
        </qti-match>
        <qti-set-outcome-value identifier="FEEDBACK">
          <qti-base-value base-type="identifier">FB_B</qti-base-value>
        </qti-set-outcome-value>
        <qti-set-outcome-value identifier="SOLUTION">
          <qti-base-value base-type="identifier">show</qti-base-value>
        </qti-set-outcome-value>
      </qti-response-else-if>
      <qti-response-else-if>
        <qti-match>
          <qti-variable identifier="RESPONSE"/>
          <qti-base-value base-type="identifier">C</qti-base-value>
        </qti-match>
        <qti-set-outcome-value identifier="FEEDBACK">
          <qti-base-value base-type="identifier">FB_C</qti-base-value>
        </qti-set-outcome-value>
        <qti-set-outcome-value identifier="SOLUTION">
          <qti-base-value base-type="identifier">show</qti-base-value>
        </qti-set-outcome-value>
      </qti-response-else-if>
      <qti-response-else-if>
        <qti-match>
          <qti-variable identifier="RESPONSE"/>
          <qti-base-value base-type="identifier">D</qti-base-value>
        </qti-match>
        <qti-set-outcome-value identifier="FEEDBACK">
          <qti-base-value base-type="identifier">FB_D</qti-base-value>
        </qti-set-outcome-value>
        <qti-set-outcome-value identifier="SOLUTION">
          <qti-base-value base-type="identifier">show</qti-base-value>
        </qti-set-outcome-value>
      </qti-response-else-if>
      <qti-response-else>
        <qti-set-outcome-value identifier="FEEDBACK">
          <qti-base-value base-type="identifier">FB_B</qti-base-value>
        </qti-set-outcome-value>
        <qti-set-outcome-value identifier="SOLUTION">
          <qti-base-value base-type="identifier">show</qti-base-value>
        </qti-set-outcome-value>
      </qti-response-else>
    </qti-response-condition>
  </qti-response-processing>
</qti-assessment-item>