{
  "sections": [
    {
      "block_name": "objective",
      "index": null,
      "html": "<header data-block=\"objective\">\n  <h1>Mini-clase: Evaluación de expresiones algebraicas</h1>\n  <p data-role=\"learning-objective\">Al terminar esta mini-clase podrás evaluar expresiones algebraicas sustituyendo números racionales y aplicando correctamente jerarquía de operaciones y signos.</p>\n  <p data-role=\"paes-relevance\">Esta habilidad aparece en preguntas de Álgebra de la PAES M1 y en muchas fórmulas usadas.</p>\n</header>",
      "word_count": 40,
      "validation_status": "passed",
      "validation_errors": []
    },
    {
      "block_name": "concept",
      "index": null,
      "html": "<section data-block=\"concept\" data-role=\"concept\">\n  <header>\n    <h2>Idea clave</h2>\n  </header>\n  <h3>Qué es evaluar una expresión</h3>\n  <p>Evaluar una expresión es reemplazar cada variable por el número racional dado (entero, fracción o decimal) y calcular el valor final paso a paso.</p>\n  <p>Si <math xmlns=\"http://www.w3.org/1998/Math/MathML\"><mrow><mi>f</mi><mo>(</mo><mi>x</mi><mo>,</mo><mi>y</mi><mo>)</mo><mo>=</mo><mn>3</mn><mi>x</mi><mo>-</mo><mn>2</mn><mi>y</mi></mrow></math> y <math xmlns=\"http://www.w3.org/1998/Math/MathML\"><mrow><mi>x</mi><mo>=</mo><mn>2</mn></mrow></math>, <math xmlns=\"http://www.w3.org/1998/Math/MathML\"><mrow><mi>y</mi><mo>=</mo><mo>-</mo><mn>1</mn></mrow></math>, reescribes con esos números y luego haces las operaciones.</p>\n  <h3>Orden y signos al calcular</h3>\n  <p>Respeta la jerarquía: paréntesis, potencias, multiplicaciones y divisiones, luego sumas y restas.</p>\n  <p>En polinomios y fracciones algebraicas simples, calcula numerador y denominador por separado y después divide, cuidando las reglas de signos.</p>\n  <h3>Trampa PAES</h3>\n  <p>❌ Confundir el cuadrado de un negativo: <math xmlns=\"http://www.w3.org/1998/Math/MathML\"><mrow><msup><mrow><mo>(</mo><mo>-</mo><mn>3</mn><mo>)</mo></mrow><mn>2</mn></msup></mrow></math> como si fuera <math xmlns=\"http://www.w3.org/1998/Math/MathML\"><mrow><mo>-</mo><msup><mn>3</mn><mn>2</mn></msup></mrow></math>.</p>\n  <p>✔ Escribe siempre el valor negativo entre paréntesis al elevar: <math xmlns=\"http://www.w3.org/1998/Math/MathML\"><mrow><msup><mrow><mo>(</mo><mo>-</mo><mn>3</mn><mo>)</mo></mrow><mn>2</mn></msup></mrow></math> da positivo, mientras que <math xmlns=\"http://www.w3.org/1998/Math/MathML\"><mrow><mo>-</mo><msup><mn>3</mn><mn>2</mn></msup></mrow></math> es negativo.</p>\n</section>",
      "word_count": 131,
      "validation_status": "passed",
      "validation_errors": []
    },
    {
      "block_name": "worked-example",
      "index": 1,
      "html": "<section data-block=\"worked-example\" data-index=\"1\">\n  <header>\n    <h2>Ejemplo resuelto</h2>\n    <p>Evalúa la función <math xmlns=\"http://www.w3.org/1998/Math/MathML\"><mrow><mi>f</mi><mo>(</mo><mi>x</mi><mo>,</mo><mi>y</mi><mo>)</mo><mo>=</mo><mfrac><mrow><mn>2</mn><msup><mi>x</mi><mn>2</mn></msup><mo>-</mo><mn>3</mn><mi>y</mi></mrow><mn>2</mn></mfrac></mrow></math> cuando <math xmlns=\"http://www.w3.org/1998/Math/MathML\"><mrow><mi>x</mi><mo>=</mo><mo>-</mo><mfrac><mn>3</mn><mn>2</mn></mfrac><mo>,</mo><mi>y</mi><mo>=</mo><mn>0,5</mn></mrow></math>. Busca un único valor numérico.</p>\n  </header>\n  <ol data-role=\"steps\">\n    <li>\n      <details>\n        <summary><strong>Paso 1:</strong> Sustituye valores con paréntesis</summary>\n        <p>Reemplaza x e y por sus valores en la fracción y escribe <math xmlns=\"http://www.w3.org/1998/Math/MathML\"><mrow><mi>f</mi><mo>(</mo><mo>-</mo><mfrac><mn>3</mn><mn>2</mn></mfrac><mo>,</mo><mn>0,5</mn><mo>)</mo><mo>=</mo><mfrac><mrow><mn>2</mn><msup><mrow><mo>(</mo><mo>-</mo><mfrac><mn>3</mn><mn>2</mn></mfrac><mo>)</mo></mrow><mn>2</mn></msup><mo>-</mo><mn>3</mn><mo>·</mo><mn>0,5</mn></mrow><mn>2</mn></mfrac></mrow></math>, usando paréntesis alrededor de <math xmlns=\"http://www.w3.org/1998/Math/MathML\"><mrow><mo>(</mo><mo>-</mo><mfrac><mn>3</mn><mn>2</mn></mfrac><mo>)</mo></mrow></math>; sin esos paréntesis muchos terminan calculando <math xmlns=\"http://www.w3.org/1998/Math/MathML\"><mrow><mo>-</mo><msup><mn>3</mn><mn>2</mn></msup></mrow></math> en vez de <math xmlns=\"http://www.w3.org/1998/Math/MathML\"><mrow><msup><mrow><mo>(</mo><mo>-</mo><mn>3</mn><mo>)</mo></mrow><mn>2</mn></msup></mrow></math> y cambian el signo.</p>\n      </details>\n    </li>\n    <li>\n      <details>\n        <summary><strong>Paso 2:</strong> Ordena la expresión según jerarquía</summary>\n        <p>Calcula primero la potencia <math xmlns=\"http://www.w3.org/1998/Math/MathML\"><mrow><msup><mrow><mo>(</mo><mo>-</mo><mfrac><mn>3</mn><mn>2</mn></mfrac><mo>)</mo></mrow><mn>2</mn></msup><mo>=</mo><mfrac><mn>9</mn><mn>4</mn></mfrac></mrow></math>, porque la jerarquía dice que las potencias van antes que multiplicaciones y restas; si multiplicaras antes de elevar, el resultado cambiaría.</p>\n      </details>\n    </li>\n    <li>\n      <details>\n        <summary><strong>Paso 3:</strong> Calcula paso a paso</summary>\n        <p>Multiplica: <math xmlns=\"http://www.w3.org/1998/Math/MathML\"><mrow><mn>2</mn><mo>·</mo><mfrac><mn>9</mn><mn>4</mn></mfrac><mo>=</mo><mfrac><mn>9</mn><mn>2</mn></mfrac></mrow></math> y usa que <math xmlns=\"http://www.w3.org/1998/Math/MathML\"><mrow><mn>3</mn><mo>·</mo><mn>0,5</mn><mo>=</mo><mfrac><mn>3</mn><mn>2</mn></mfrac></mrow></math>, para que el numerador quede <math xmlns=\"http://www.w3.org/1998/Math/MathML\"><mrow><mfrac><mn>9</mn><mn>2</mn></mfrac><mo>-</mo><mfrac><mn>3</mn><mn>2</mn></mfrac></mrow></math>.</p>\n        <p>Como las fracciones tienen el mismo denominador, resta solo numeradores, obtienes <math xmlns=\"http://www.w3.org/1998/Math/MathML\"><mrow><mfrac><mn>6</mn><mn>2</mn></mfrac><mo>=</mo><mn>3</mn></mrow></math> y luego divide ese 3 entre 2 para llegar a <math xmlns=\"http://www.w3.org/1998/Math/MathML\"><mrow><mfrac><mn>3</mn><mn>2</mn></mfrac></mrow></math>.</p>\n      </details>\n    </li>\n    <li>\n      <details>\n        <summary><strong>Paso 4:</strong> Verifica el resultado final</summary>\n        <p>Comprueba con decimales: <math xmlns=\"http://www.w3.org/1998/Math/MathML\"><mrow><msup><mrow><mo>(</mo><mo>-</mo><mn>1,5</mn><mo>)</mo></mrow><mn>2</mn></msup><mo>=</mo><mn>2,25</mn></mrow></math>, luego <math xmlns=\"http://www.w3.org/1998/Math/MathML\"><mrow><mn>2</mn><mo>·</mo><mn>2,25</mn><mo>=</mo><mn>4,5</mn></mrow></math> y <math xmlns=\"http://www.w3.org/1998/Math/MathML\"><mrow><mn>3</mn><mo>·</mo><mn>0,5</mn><mo>=</mo><mn>1,5</mn></mrow></math>, así que el numerador es <math xmlns=\"http://www.w3.org/1998/Math/MathML\"><mn>3</mn></math>.</p>\n        <p>Al dividir ese numerador entre el 2 del denominador obtienes <math xmlns=\"http://www.w3.org/1998/Math/MathML\"><mn>1,5</mn></math>, que coincide con <math xmlns=\"http://www.w3.org/1998/Math/MathML\"><mfrac><mn>3</mn><mn>2</mn></mfrac></math>, así que el resultado <math xmlns=\"http://www.w3.org/1998/Math/MathML\"><mfrac><mn>3</mn><mn>2</mn></mfrac></math> es consistente.</p>\n      </details>\n    </li>\n  </ol>\n  <p data-role=\"micro-reinforcement\">Si obtuviste <math xmlns=\"http://www.w3.org/1998/Math/MathML\"><mrow><mi>f</mi><mo>(</mo><mo>-</mo><mfrac><mn>3</mn><mn>2</mn></mfrac><mo>,</mo><mn>0,5</mn><mo>)</mo><mo>=</mo><mfrac><mn>3</mn><mn>2</mn></mfrac></mrow></math>, vas bien — el punto clave fue respetar la jerarquía de operaciones y encerrar el -3/2 entre paréntesis al elevarlo al cuadrado.</p>\n  <ul data-role=\"paes-checklist\">\n    <li>✅ ¿Reemplacé todas las variables y puse paréntesis en cada valor negativo?</li>\n    <li>✅ ¿Apliqué el orden: potencias, luego multiplicaciones/divisiones, luego sumas/restas?</li>\n    <li>✅ ¿Calculé numerador y denominador y llegué a un único valor final correcto?</li>\n  </ul>\n</section>",
      "word_count": 280,
      "validation_status": "passed",
      "validation_errors": []
    }
  ]
}