<qti-assessment-item xmlns="http://www.imsglobal.org/xsd/imsqtiasi_v3p0" xmlns:xsi="http://www.w3.org/2001/XMLSchema-instance" xsi:schemaLocation="http://www.imsglobal.org/xsd/imsqtiasi_v3p0 https://purl.imsglobal.org/spec/qti/v3p0/schema/xsd/imsqti_asiv3p0_v1p0.xsd" identifier="question-31" title="Ecuación de compra de bebidas y jugos" adaptive="false" time-dependent="false">
  <qti-response-declaration identifier="RESPONSE" cardinality="single" base-type="identifier">
    <qti-correct-response>
      <qti-value>ChoiceC</qti-value>
    </qti-correct-response>
  </qti-response-declaration>
  <qti-outcome-declaration identifier="FEEDBACK" cardinality="single" base-type="identifier"/>
  <qti-outcome-declaration identifier="SOLUTION" cardinality="single" base-type="identifier"/>
  <qti-outcome-declaration identifier="SCORE" cardinality="single" base-type="float">
    <qti-default-value>
      <qti-value>0</qti-value>
    </qti-default-value>
  </qti-outcome-declaration>
  <qti-item-body>
    <p>Para una fiesta se compraron tres botellas de jugo del mismo precio y tres botellas de bebidas del mismo precio, gastándose en total $16 770.</p>
    <p>Una botella de bebida es $390 más cara que una botella de jugo.</p>
    <qti-choice-interaction max-choices="1" response-identifier="RESPONSE">
      <qti-prompt>¿Cuál de las siguientes ecuaciones permite determinar el precio x de una botella de jugo, en pesos?</qti-prompt>
      <qti-simple-choice identifier="ChoiceA">
        <math xmlns="http://www.w3.org/1998/Math/MathML" display="inline">
          <mn>3</mn>
          <mi>x</mi>
          <mo>+</mo>
          <mn>390</mn>
          <mo>=</mo>
          <mn>16</mn>
          <mspace width="thickmathspace"/>
          <mn>770</mn>
        </math>
        <qti-feedback-inline identifier="FeedbackA" outcome-identifier="FEEDBACK" show-hide="show">Incorrecto. En esta ecuación solo se considera el precio de las 3 botellas de jugo y se suma 390, pero no se está representando el precio de las 3 botellas de bebida. El precio total debe incluir el costo de las 3 botellas de jugo y de las 3 botellas de bebida. Si el jugo cuesta <math xmlns="http://www.w3.org/1998/Math/MathML" display="inline"><mi>x</mi></math> pesos, entonces la bebida cuesta <math xmlns="http://www.w3.org/1998/Math/MathML" display="inline"><mi>x</mi><mo>+</mo><mn>390</mn></math> pesos, por lo que el total debe ser <math xmlns="http://www.w3.org/1998/Math/MathML" display="inline"><mn>3</mn><mi>x</mi><mo>+</mo><mn>3</mn><mo>(</mo><mi>x</mi><mo>+</mo><mn>390</mn><mo>)</mo></math>, no solo <math xmlns="http://www.w3.org/1998/Math/MathML" display="inline"><mn>3</mn><mi>x</mi><mo>+</mo><mn>390</mn></math>.</qti-feedback-inline>
      </qti-simple-choice>
      <qti-simple-choice identifier="ChoiceB">
        <math xmlns="http://www.w3.org/1998/Math/MathML" display="inline">
          <mn>6</mn>
          <mi>x</mi>
          <mo>+</mo>
          <mn>390</mn>
          <mo>=</mo>
          <mn>16</mn>
          <mspace width="thickmathspace"/>
          <mn>770</mn>
        </math>
        <qti-feedback-inline identifier="FeedbackB" outcome-identifier="FEEDBACK" show-hide="show">Incorrecto. En esta ecuación se está sumando 390 solo una vez, como si el recargo de 390 pesos se aplicara a una sola botella, pero en el problema hay 3 botellas de bebida, cada una 390 pesos más cara que el jugo. Si el jugo cuesta <math xmlns="http://www.w3.org/1998/Math/MathML" display="inline"><mi>x</mi></math> pesos, el total correcto debe ser <math xmlns="http://www.w3.org/1998/Math/MathML" display="inline"><mn>3</mn><mi>x</mi><mo>+</mo><mn>3</mn><mo>(</mo><mi>x</mi><mo>+</mo><mn>390</mn><mo>)</mo></math>, donde el término <math xmlns="http://www.w3.org/1998/Math/MathML" display="inline"><mn>3</mn><mo>(</mo><mi>x</mi><mo>+</mo><mn>390</mn><mo>)</mo></math> representa el precio de las 3 botellas de bebida, no solo una suma única de 390.</qti-feedback-inline>
      </qti-simple-choice>
      <qti-simple-choice identifier="ChoiceC">
        <math xmlns="http://www.w3.org/1998/Math/MathML" display="inline">
          <mn>3</mn>
          <mi>x</mi>
          <mo>+</mo>
          <mn>3</mn>
          <mo>(</mo>
          <mi>x</mi>
          <mo>+</mo>
          <mn>390</mn>
          <mo>)</mo>
          <mo>=</mo>
          <mn>16</mn>
          <mspace width="thickmathspace"/>
          <mn>770</mn>
        </math>
        <qti-feedback-inline identifier="FeedbackC" outcome-identifier="FEEDBACK" show-hide="show">¡Correcto! Si el precio de una botella de jugo es <math xmlns="http://www.w3.org/1998/Math/MathML" display="inline"><mi>x</mi></math> pesos, entonces el precio de una botella de bebida es <math xmlns="http://www.w3.org/1998/Math/MathML" display="inline"><mi>x</mi><mo>+</mo><mn>390</mn></math> pesos, porque es 390 pesos más cara. El precio de las 3 botellas de jugo es <math xmlns="http://www.w3.org/1998/Math/MathML" display="inline"><mn>3</mn><mi>x</mi></math> y el precio de las 3 botellas de bebida es <math xmlns="http://www.w3.org/1998/Math/MathML" display="inline"><mn>3</mn><mo>(</mo><mi>x</mi><mo>+</mo><mn>390</mn><mo>)</mo></math>. La suma de ambos debe ser 16.770 pesos, por lo que la ecuación correcta es <math xmlns="http://www.w3.org/1998/Math/MathML" display="inline"><mn>3</mn><mi>x</mi><mo>+</mo><mn>3</mn><mo>(</mo><mi>x</mi><mo>+</mo><mn>390</mn><mo>)</mo><mo>=</mo><mn>16</mn><mspace width="thickmathspace"/><mn>770</mn></math>.</qti-feedback-inline>
      </qti-simple-choice>
      <qti-simple-choice identifier="ChoiceD">
        <math xmlns="http://www.w3.org/1998/Math/MathML" display="inline">
          <mn>3</mn>
          <mi>x</mi>
          <mo>+</mo>
          <mn>3</mn>
          <mo>(</mo>
          <mi>x</mi>
          <mo>-</mo>
          <mn>390</mn>
          <mo>)</mo>
          <mo>=</mo>
          <mn>16</mn>
          <mspace width="thickmathspace"/>
          <mn>770</mn>
        </math>
        <qti-feedback-inline identifier="FeedbackD" outcome-identifier="FEEDBACK" show-hide="show">Incorrecto. En esta ecuación se está restando 390, como si la bebida fuera 390 pesos más barata que el jugo, pero el enunciado dice que una botella de bebida es 390 pesos más cara que una botella de jugo. Si el jugo cuesta <math xmlns="http://www.w3.org/1998/Math/MathML" display="inline"><mi>x</mi></math> pesos, la bebida debe costar <math xmlns="http://www.w3.org/1998/Math/MathML" display="inline"><mi>x</mi><mo>+</mo><mn>390</mn></math> y no <math xmlns="http://www.w3.org/1998/Math/MathML" display="inline"><mi>x</mi><mo>-</mo><mn>390</mn></math>. Por eso, el término correcto para las 3 bebidas es <math xmlns="http://www.w3.org/1998/Math/MathML" display="inline"><mn>3</mn><mo>(</mo><mi>x</mi><mo>+</mo><mn>390</mn><mo>)</mo></math>, no <math xmlns="http://www.w3.org/1998/Math/MathML" display="inline"><mn>3</mn><mo>(</mo><mi>x</mi><mo>-</mo><mn>390</mn><mo>)</mo></math>.</qti-feedback-inline>
      </qti-simple-choice>
    </qti-choice-interaction>
    <qti-feedback-block identifier="show" outcome-identifier="SOLUTION" show-hide="show">
      <qti-content-body>
        <p><strong>Resolución paso a paso</strong></p>
        <ol>
          <li>
            <p>Sea <math xmlns="http://www.w3.org/1998/Math/MathML" display="inline"><mi>x</mi></math> el precio, en pesos, de una botella de jugo.</p>
          </li>
          <li>
            <p>Como una botella de bebida es 390 pesos más cara que una botella de jugo, el precio de una botella de bebida es:</p>
            <p>
              <math xmlns="http://www.w3.org/1998/Math/MathML" display="block">
                <mi>x</mi>
                <mo>+</mo>
                <mn>390</mn>
              </math>
            </p>
          </li>
          <li>
            <p>Se compran 3 botellas de jugo, por lo que el costo total de los jugos es:</p>
            <p>
              <math xmlns="http://www.w3.org/1998/Math/MathML" display="block">
                <mn>3</mn>
                <mi>x</mi>
              </math>
            </p>
          </li>
          <li>
            <p>Se compran 3 botellas de bebida, por lo que el costo total de las bebidas es:</p>
            <p>
              <math xmlns="http://www.w3.org/1998/Math/MathML" display="block">
                <mn>3</mn>
                <mo>(</mo>
                <mi>x</mi>
                <mo>+</mo>
                <mn>390</mn>
                <mo>)</mo>
              </math>
            </p>
          </li>
          <li>
            <p>El gasto total en jugos y bebidas es 16.770 pesos, por lo que la ecuación que representa la situación es:</p>
            <p>
              <math xmlns="http://www.w3.org/1998/Math/MathML" display="block">
                <mn>3</mn>
                <mi>x</mi>
                <mo>+</mo>
                <mn>3</mn>
                <mo>(</mo>
                <mi>x</mi>
                <mo>+</mo>
                <mn>390</mn>
                <mo>)</mo>
                <mo>=</mo>
                <mn>16</mn>
                <mspace width="thickmathspace"/>
                <mn>770</mn>
              </math>
            </p>
          </li>
          <li>
            <p>Desarrollamos la expresión del lado izquierdo:</p>
            <p>Primero distribuimos el 3 en el paréntesis:</p>
            <p>
              <math xmlns="http://www.w3.org/1998/Math/MathML" display="block">
                <mn>3</mn>
                <mi>x</mi>
                <mo>+</mo>
                <mn>3</mn>
                <mo>(</mo>
                <mi>x</mi>
                <mo>+</mo>
                <mn>390</mn>
                <mo>)</mo>
                <mo>=</mo>
                <mn>3</mn>
                <mi>x</mi>
                <mo>+</mo>
                <mn>3</mn>
                <mi>x</mi>
                <mo>+</mo>
                <mn>3</mn>
                <mo>&#x00D7;</mo>
                <mn>390</mn>
              </math>
            </p>
            <p>Calculamos <math xmlns="http://www.w3.org/1998/Math/MathML" display="inline"><mn>3</mn><mo>&#x00D7;</mo><mn>390</mn></math> paso a paso:</p>
            <p>
              <math xmlns="http://www.w3.org/1998/Math/MathML" display="block">
                <mn>3</mn>
                <mo>&#x00D7;</mo>
                <mn>390</mn>
                <mo>=</mo>
                <mn>3</mn>
                <mo>&#x00D7;</mo>
                <mn>39</mn>
                <mo>&#x00D7;</mo>
                <mn>10</mn>
                <mo>=</mo>
                <mn>117</mn>
                <mo>&#x00D7;</mo>
                <mn>10</mn>
                <mo>=</mo>
                <mn>1.170</mn>
              </math>
            </p>
            <p>Entonces la expresión queda:</p>
            <p>
              <math xmlns="http://www.w3.org/1998/Math/MathML" display="block">
                <mn>3</mn>
                <mi>x</mi>
                <mo>+</mo>
                <mn>3</mn>
                <mi>x</mi>
                <mo>+</mo>
                <mn>1.170</mn>
              </math>
            </p>
          </li>
          <li>
            <p>Sumamos los términos semejantes <math xmlns="http://www.w3.org/1998/Math/MathML" display="inline"><mn>3</mn><mi>x</mi></math> y <math xmlns="http://www.w3.org/1998/Math/MathML" display="inline"><mn>3</mn><mi>x</mi></math>:</p>
            <p>
              <math xmlns="http://www.w3.org/1998/Math/MathML" display="block">
                <mn>3</mn>
                <mi>x</mi>
                <mo>+</mo>
                <mn>3</mn>
                <mi>x</mi>
                <mo>=</mo>
                <mn>6</mn>
                <mi>x</mi>
              </math>
            </p>
            <p>La ecuación queda entonces:</p>
            <p>
              <math xmlns="http://www.w3.org/1998/Math/MathML" display="block">
                <mn>6</mn>
                <mi>x</mi>
                <mo>+</mo>
                <mn>1.170</mn>
                <mo>=</mo>
                <mn>16</mn>
                <mspace width="thickmathspace"/>
                <mn>770</mn>
              </math>
            </p>
          </li>
          <li>
            <p>Restamos 1.170 en ambos lados de la ecuación para despejar el término con <math xmlns="http://www.w3.org/1998/Math/MathML" display="inline"><mi>x</mi></math>:</p>
            <p>Calculamos <math xmlns="http://www.w3.org/1998/Math/MathML" display="inline"><mn>16.770</mn><mo>-</mo><mn>1.170</mn></math> paso a paso:</p>
            <p>
              <math xmlns="http://www.w3.org/1998/Math/MathML" display="block">
                <mn>16.770</mn>
                <mo>-</mo>
                <mn>1.170</mn>
                <mo>=</mo>
                <mn>15.600</mn>
              </math>
            </p>
            <p>Entonces:</p>
            <p>
              <math xmlns="http://www.w3.org/1998/Math/MathML" display="block">
                <mn>6</mn>
                <mi>x</mi>
                <mo>=</mo>
                <mn>15.600</mn>
              </math>
            </p>
          </li>
          <li>
            <p>Dividimos ambos lados de la ecuación por 6 para encontrar el valor de <math xmlns="http://www.w3.org/1998/Math/MathML" display="inline"><mi>x</mi></math>:</p>
            <p>Calculamos <math xmlns="http://www.w3.org/1998/Math/MathML" display="inline"><mn>15.600</mn><mo>&#x00F7;</mo><mn>6</mn></math> paso a paso:</p>
            <p>Primero notamos que <math xmlns="http://www.w3.org/1998/Math/MathML" display="inline"><mn>15.600</mn><mo>=</mo><mn>156</mn><mo>&#x00D7;</mo><mn>100</mn></math>. Luego:</p>
            <p>
              <math xmlns="http://www.w3.org/1998/Math/MathML" display="block">
                <mn>156</mn>
                <mo>&#x00F7;</mo>
                <mn>6</mn>
                <mo>=</mo>
                <mn>26</mn>
              </math>
            </p>
            <p>Por lo tanto:</p>
            <p>
              <math xmlns="http://www.w3.org/1998/Math/MathML" display="block">
                <mn>15.600</mn>
                <mo>&#x00F7;</mo>
                <mn>6</mn>
                <mo>=</mo>
                <mn>26</mn>
                <mo>&#x00D7;</mo>
                <mn>100</mn>
                <mo>=</mo>
                <mn>2.600</mn>
              </math>
            </p>
            <p>Así, el precio de una botella de jugo es:</p>
            <p>
              <math xmlns="http://www.w3.org/1998/Math/MathML" display="block">
                <mi>x</mi>
                <mo>=</mo>
                <mn>2.600</mn>
              </math>
            </p>
          </li>
          <li>
            <p>Verificamos que este valor cumple con el enunciado:</p>
            <p>Precio de una botella de jugo: 2.600 pesos.</p>
            <p>Precio de una botella de bebida: 2.600 + 390 = 2.990 pesos.</p>
            <p>Calculamos el gasto total:</p>
            <p>Gasto en jugos:</p>
            <p>
              <math xmlns="http://www.w3.org/1998/Math/MathML" display="block">
                <mn>3</mn>
                <mo>&#x00D7;</mo>
                <mn>2.600</mn>
                <mo>=</mo>
                <mn>7.800</mn>
              </math>
            </p>
            <p>Gasto en bebidas:</p>
            <p>
              <math xmlns="http://www.w3.org/1998/Math/MathML" display="block">
                <mn>3</mn>
                <mo>&#x00D7;</mo>
                <mn>2.990</mn>
                <mo>=</mo>
                <mn>8.970</mn>
              </math>
            </p>
            <p>Suma total:</p>
            <p>
              <math xmlns="http://www.w3.org/1998/Math/MathML" display="block">
                <mn>7.800</mn>
                <mo>+</mo>
                <mn>8.970</mn>
                <mo>=</mo>
                <mn>16.770</mn>
              </math>
            </p>
            <p>El total coincide con los 16.770 pesos del problema, por lo que la ecuación planteada es correcta y permite determinar el precio de una botella de jugo.</p>
          </li>
        </ol>
      </qti-content-body>
    </qti-feedback-block>
  </qti-item-body>
  <qti-response-processing>
    <qti-response-condition>
      <qti-response-if>
        <qti-match>
          <qti-variable identifier="RESPONSE"/>
          <qti-base-value base-type="identifier">ChoiceC</qti-base-value>
        </qti-match>
        <qti-set-outcome-value identifier="SCORE">
          <qti-base-value base-type="float">1</qti-base-value>
        </qti-set-outcome-value>
        <qti-set-outcome-value identifier="FEEDBACK">
          <qti-base-value base-type="identifier">FeedbackC</qti-base-value>
        </qti-set-outcome-value>
        <qti-set-outcome-value identifier="SOLUTION">
          <qti-base-value base-type="identifier">show</qti-base-value>
        </qti-set-outcome-value>
      </qti-response-if>
      <qti-response-else-if>
        <qti-match>
          <qti-variable identifier="RESPONSE"/>
          <qti-base-value base-type="identifier">ChoiceA</qti-base-value>
        </qti-match>
        <qti-set-outcome-value identifier="SCORE">
          <qti-base-value base-type="float">0</qti-base-value>
        </qti-set-outcome-value>
        <qti-set-outcome-value identifier="FEEDBACK">
          <qti-base-value base-type="identifier">FeedbackA</qti-base-value>
        </qti-set-outcome-value>
        <qti-set-outcome-value identifier="SOLUTION">
          <qti-base-value base-type="identifier">show</qti-base-value>
        </qti-set-outcome-value>
      </qti-response-else-if>
      <qti-response-else-if>
        <qti-match>
          <qti-variable identifier="RESPONSE"/>
          <qti-base-value base-type="identifier">ChoiceB</qti-base-value>
        </qti-match>
        <qti-set-outcome-value identifier="SCORE">
          <qti-base-value base-type="float">0</qti-base-value>
        </qti-set-outcome-value>
        <qti-set-outcome-value identifier="FEEDBACK">
          <qti-base-value base-type="identifier">FeedbackB</qti-base-value>
        </qti-set-outcome-value>
        <qti-set-outcome-value identifier="SOLUTION">
          <qti-base-value base-type="identifier">show</qti-base-value>
        </qti-set-outcome-value>
      </qti-response-else-if>
      <qti-response-else-if>
        <qti-match>
          <qti-variable identifier="RESPONSE"/>
          <qti-base-value base-type="identifier">ChoiceD</qti-base-value>
        </qti-match>
        <qti-set-outcome-value identifier="SCORE">
          <qti-base-value base-type="float">0</qti-base-value>
        </qti-set-outcome-value>
        <qti-set-outcome-value identifier="FEEDBACK">
          <qti-base-value base-type="identifier">FeedbackD</qti-base-value>
        </qti-set-outcome-value>
        <qti-set-outcome-value identifier="SOLUTION">
          <qti-base-value base-type="identifier">show</qti-base-value>
        </qti-set-outcome-value>
      </qti-response-else-if>
      <qti-response-else>
        <qti-set-outcome-value identifier="SCORE">
          <qti-base-value base-type="float">0</qti-base-value>
        </qti-set-outcome-value>
        <qti-set-outcome-value identifier="FEEDBACK">
          <qti-base-value base-type="identifier">FeedbackA</qti-base-value>
        </qti-set-outcome-value>
        <qti-set-outcome-value identifier="SOLUTION">
          <qti-base-value base-type="identifier">show</qti-base-value>
        </qti-set-outcome-value>
      </qti-response-else>
    </qti-response-condition>
  </qti-response-processing>
</qti-assessment-item>