<qti-assessment-item xmlns="http://www.imsglobal.org/xsd/imsqtiasi_v3p0" xmlns:xsi="http://www.w3.org/2001/XMLSchema-instance" identifier="Q48_v5" title="Q48_v5" time-dependent="false" adaptive="false" xsi:schemaLocation="http://www.imsglobal.org/xsd/imsqtiasi_v3p0 https://purl.imsglobal.org/spec/qti/v3p0/schema/xsd/imsqti_asiv3p0_v1p0.xsd">
  <qti-response-declaration identifier="RESPONSE" cardinality="single" base-type="identifier">
    <qti-correct-response>
      <qti-value>ChoiceD</qti-value>
    </qti-correct-response>
  </qti-response-declaration>
  <qti-outcome-declaration identifier="FEEDBACK" cardinality="single" base-type="identifier"/>
  <qti-outcome-declaration identifier="SOLUTION" cardinality="single" base-type="identifier"/>
  <qti-outcome-declaration identifier="SCORE" cardinality="single" base-type="float"><qti-default-value><qti-value>0</qti-value></qti-default-value></qti-outcome-declaration><qti-item-body>
    <p>Considera la siguiente técnica para hacer figuras con una hoja de papel:</p>
    <p>• Primero se dobla la hoja de papel exactamente por la mitad, de modo que ambas partes coincidan al superponerse.
      <br />
      <img src="requiere_nueva_imagen.png" alt="Diagrama de una hoja de papel rectangular vista de frente, con una línea punteada vertical en el centro que indica el pliegue. A la derecha se ve la mitad derecha de la hoja doblándose hacia atrás hasta superponerse con la mitad izquierda." />
    </p>
    <p>• Luego se dibuja solo la mitad de una figura sobre el borde del pliegue, se recorta siguiendo ese contorno y, por último, se desdobla el papel. La figura resultante queda formada por dos mitades que son imágenes especulares una de la otra, respecto del pliegue.</p>
    <p>En la siguiente figura se muestran cuatro siluetas que ya fueron recortadas. Las figuras están etiquetadas como A, B, C y D.</p>
    <p>
      <img src="requiere_nueva_imagen.png" alt="Ilustración con cuatro siluetas negras etiquetadas A, B, C y D. A es un corazón perfectamente simétrico respecto a un eje vertical. B es una hoja de árbol idealizada, con un contorno liso y el nervio central vertical, de modo que el lado izquierdo y el derecho son simétricos. C es una mariposa esquemática vista de frente, con dos alas idénticas a cada lado de un cuerpo central vertical. D es una flecha curva que apunta hacia arriba pero se curva solo hacia la derecha, sin ningún eje de simetría posible; la curva no se repite hacia el lado izquierdo." />
    </p>
    <p>Todas estas figuras se hicieron recortando una sola vez una hoja doblada por la mitad, excepto una. ¿Cuál NO se puede obtener usando solo este procedimiento?</p>
    <qti-choice-interaction response-identifier="RESPONSE" shuffle="false" max-choices="1">
      
      <qti-simple-choice identifier="ChoiceA">A<qti-feedback-inline identifier="FB_ChoiceA" outcome-identifier="FEEDBACK">Incorrecto. La figura A sí puede obtenerse con este procedimiento porque al desdoblar aparecen dos mitades iguales respecto del pliegue vertical. El corazón mostrado tiene simetría axial vertical, por lo que puede formarse recortando solo una mitad y reflejándola al abrir el papel.</qti-feedback-inline></qti-simple-choice>
      
      <qti-simple-choice identifier="ChoiceB">B<qti-feedback-inline identifier="FB_ChoiceB" outcome-identifier="FEEDBACK">Incorrecto. La figura B sí puede obtenerse con este procedimiento porque sus lados izquierdo y derecho son imágenes especulares respecto de un eje vertical. Esa simetría coincide con el pliegue, así que basta recortar una mitad para que al desdoblar aparezca la figura completa.</qti-feedback-inline></qti-simple-choice>
      
      <qti-simple-choice identifier="ChoiceC">C<qti-feedback-inline identifier="FB_ChoiceC" outcome-identifier="FEEDBACK">Incorrecto. La figura C sí puede obtenerse con este procedimiento porque la mariposa tiene un cuerpo central y dos alas simétricas a ambos lados de un eje vertical. Al doblar por ese eje, recortar una mitad y desdoblar, se obtiene la figura completa.</qti-feedback-inline></qti-simple-choice>
      <qti-simple-choice identifier="ChoiceD">D<qti-feedback-inline identifier="FB_ChoiceD" outcome-identifier="FEEDBACK">¡Correcto! La figura D no puede obtenerse con este procedimiento. Al recortar una hoja doblada y luego desdoblarla, la figura final siempre queda formada por dos mitades que son imágenes especulares respecto del pliegue. En D eso no ocurre, porque la curva aparece hacia un solo lado y no existe una mitad reflejada al otro lado del eje.</qti-feedback-inline></qti-simple-choice>
    </qti-choice-interaction>
    <qti-feedback-block identifier="show" outcome-identifier="SOLUTION" show-hide="show">
      <qti-content-body>
        <p><strong>Resolución paso a paso</strong></p>
        <ol>
          <li>
            <p><strong>Paso 1: Identificar la propiedad del procedimiento</strong></p>
            <p>Cuando una hoja se dobla exactamente por la mitad y se recorta una figura apoyada en el borde del pliegue, al desdoblarla se obtienen dos partes que son reflejo una de la otra respecto de ese pliegue.</p>
          </li>
          <li>
            <p><strong>Paso 2: Concluir qué tipo de figuras se pueden formar</strong></p>
            <p>Por lo tanto, cualquier figura obtenida de esta manera debe tener un eje de simetría coincidente con el pliegue. En este caso, el eje de simetría es vertical.</p>
          </li>
          <li>
            <p><strong>Paso 3: Revisar cada alternativa</strong></p>
            <p>A: el corazón tiene simetría vertical, así que sí se puede obtener.</p>
            <p>B: la hoja mostrada tiene lado izquierdo y lado derecho simétricos, así que sí se puede obtener.</p>
            <p>C: la mariposa tiene dos alas simétricas respecto de un eje vertical, así que sí se puede obtener.</p>
            <p>D: la flecha curva no tiene simetría axial vertical. Su forma se curva hacia un solo lado y no aparece una parte reflejada al otro lado del eje.</p>
          </li>
          <li>
            <p><strong>Paso 4: Determinar la figura que no cumple la condición</strong></p>
            <p>La única figura que no puede salir de un solo recorte hecho sobre una hoja doblada por la mitad es la que no tiene simetría respecto del pliegue.</p>
          </li>
          <li>
            <p><strong>Conclusión</strong></p>
            <p>La figura que NO se puede obtener usando solo este procedimiento es la alternativa D.</p>
          </li>
        </ol>
      </qti-content-body>
    </qti-feedback-block>
  </qti-item-body>
  <qti-response-processing>
    <qti-response-condition>
      <qti-response-if>
        <qti-match>
          <qti-variable identifier="RESPONSE"/>
          <qti-base-value base-type="identifier">ChoiceD</qti-base-value>
        </qti-match>
        <qti-set-outcome-value identifier="SCORE">
          <qti-base-value base-type="float">1</qti-base-value>
        </qti-set-outcome-value>
        <qti-set-outcome-value identifier="FEEDBACK">
          <qti-base-value base-type="identifier">FB_ChoiceD</qti-base-value>
        </qti-set-outcome-value>
        <qti-set-outcome-value identifier="SOLUTION">
          <qti-base-value base-type="identifier">show</qti-base-value>
        </qti-set-outcome-value>
      </qti-response-if>
      <qti-response-else-if>
        <qti-match>
          <qti-variable identifier="RESPONSE"/>
          <qti-base-value base-type="identifier">ChoiceA</qti-base-value>
        </qti-match>
        <qti-set-outcome-value identifier="FEEDBACK">
          <qti-base-value base-type="identifier">FB_ChoiceA</qti-base-value>
        </qti-set-outcome-value>
        <qti-set-outcome-value identifier="SOLUTION">
          <qti-base-value base-type="identifier">show</qti-base-value>
        </qti-set-outcome-value>
      </qti-response-else-if>
      <qti-response-else-if>
        <qti-match>
          <qti-variable identifier="RESPONSE"/>
          <qti-base-value base-type="identifier">ChoiceB</qti-base-value>
        </qti-match>
        <qti-set-outcome-value identifier="FEEDBACK">
          <qti-base-value base-type="identifier">FB_ChoiceB</qti-base-value>
        </qti-set-outcome-value>
        <qti-set-outcome-value identifier="SOLUTION">
          <qti-base-value base-type="identifier">show</qti-base-value>
        </qti-set-outcome-value>
      </qti-response-else-if>
      <qti-response-else-if>
        <qti-match>
          <qti-variable identifier="RESPONSE"/>
          <qti-base-value base-type="identifier">ChoiceC</qti-base-value>
        </qti-match>
        <qti-set-outcome-value identifier="FEEDBACK">
          <qti-base-value base-type="identifier">FB_ChoiceC</qti-base-value>
        </qti-set-outcome-value>
        <qti-set-outcome-value identifier="SOLUTION">
          <qti-base-value base-type="identifier">show</qti-base-value>
        </qti-set-outcome-value>
      </qti-response-else-if>
      <qti-response-else>
        <qti-set-outcome-value identifier="FEEDBACK">
          <qti-base-value base-type="identifier">FB_ChoiceA</qti-base-value>
        </qti-set-outcome-value>
        <qti-set-outcome-value identifier="SOLUTION">
          <qti-base-value base-type="identifier">show</qti-base-value>
        </qti-set-outcome-value>
      </qti-response-else>
    </qti-response-condition>
  </qti-response-processing>
</qti-assessment-item>