<qti-assessment-item xmlns="http://www.imsglobal.org/xsd/imsqtiasi_v3p0" xmlns:xsi="http://www.w3.org/2001/XMLSchema-instance" identifier="Q22_v9" title="Q22_v9" time-dependent="false" adaptive="false" xsi:schemaLocation="http://www.imsglobal.org/xsd/imsqtiasi_v3p0 https://purl.imsglobal.org/spec/qti/v3p0/schema/xsd/imsqti_asiv3p0_v1p0.xsd">
  <qti-response-declaration identifier="RESPONSE" cardinality="single" base-type="identifier">
    <qti-correct-response>
      <qti-value>ChoiceB</qti-value>
    </qti-correct-response>
  </qti-response-declaration>
  <qti-outcome-declaration identifier="FEEDBACK" cardinality="single" base-type="identifier"/>
  <qti-outcome-declaration identifier="SOLUTION" cardinality="single" base-type="identifier"/>
  <qti-outcome-declaration identifier="SCORE" cardinality="single" base-type="float">
    <qti-default-value>
      <qti-value>0</qti-value>
    </qti-default-value>
  </qti-outcome-declaration>
  <qti-item-body>
    <p>En el registro mensual de descargas de una aplicación se anotó lo siguiente:<br />- Descargas en el primer mes: 1 800 000<br />- Descargas adicionales en el segundo mes, respecto del primero: 90 000</p>
    <p>¿Qué porcentaje de aumento representaron las descargas adicionales del segundo mes respecto de las del primer mes?</p>
    <qti-choice-interaction response-identifier="RESPONSE" shuffle="true" max-choices="1">
      <qti-simple-choice identifier="ChoiceA">4,8 %<qti-feedback-inline identifier="FB_ChoiceA" outcome-identifier="FEEDBACK">Incorrecto. Si el aumento fuera de 4,8 %, entonces correspondería calcular <math xmlns="http://www.w3.org/1998/Math/MathML"><mrow><mn>1&#160;800&#160;000</mn><mo>×</mo><mfrac><mn>4,8</mn><mn>100</mn></mfrac><mo>=</mo><mn>1&#160;800&#160;000</mn><mo>×</mo><mn>0,048</mn><mo>=</mo><mn>86&#160;400</mn></mrow></math>. Pero el enunciado indica <math xmlns="http://www.w3.org/1998/Math/MathML"><mn>90&#160;000</mn></math> descargas adicionales, y <math xmlns="http://www.w3.org/1998/Math/MathML"><mn>86&#160;400</mn></math> no coincide con <math xmlns="http://www.w3.org/1998/Math/MathML"><mn>90&#160;000</mn></math>.</qti-feedback-inline></qti-simple-choice>
      <qti-simple-choice identifier="ChoiceB">5 %<qti-feedback-inline identifier="FB_ChoiceB" outcome-identifier="FEEDBACK">¡Correcto! El porcentaje de aumento se calcula comparando las descargas adicionales con las del primer mes: <math xmlns="http://www.w3.org/1998/Math/MathML"><mrow><mfrac><mn>90&#160;000</mn><mn>1&#160;800&#160;000</mn></mfrac><mo>=</mo><mfrac><mn>9</mn><mn>180</mn></mfrac><mo>=</mo><mfrac><mn>1</mn><mn>20</mn></mfrac><mo>=</mo><mn>0,05</mn></mrow></math>. Al convertir a porcentaje, <math xmlns="http://www.w3.org/1998/Math/MathML"><mrow><mn>0,05</mn><mo>×</mo><mn>100</mn><mo>=</mo><mn>5</mn></mrow></math>, por lo tanto el aumento fue de <math xmlns="http://www.w3.org/1998/Math/MathML"><mn>5</mn></math> %.</qti-feedback-inline></qti-simple-choice>
      <qti-simple-choice identifier="ChoiceC">90 %<qti-feedback-inline identifier="FB_ChoiceC" outcome-identifier="FEEDBACK">Incorrecto. Si el aumento fuera de 90 %, entonces las descargas adicionales serían <math xmlns="http://www.w3.org/1998/Math/MathML"><mrow><mn>1&#160;800&#160;000</mn><mo>×</mo><mfrac><mn>90</mn><mn>100</mn></mfrac><mo>=</mo><mn>1&#160;800&#160;000</mn><mo>×</mo><mn>0,9</mn><mo>=</mo><mn>1&#160;620&#160;000</mn></mrow></math>. Pero el enunciado indica solo <math xmlns="http://www.w3.org/1998/Math/MathML"><mn>90&#160;000</mn></math> descargas adicionales, y <math xmlns="http://www.w3.org/1998/Math/MathML"><mn>1&#160;620&#160;000</mn></math> no coincide con <math xmlns="http://www.w3.org/1998/Math/MathML"><mn>90&#160;000</mn></math>.</qti-feedback-inline></qti-simple-choice>
      <qti-simple-choice identifier="ChoiceD">50 %<qti-feedback-inline identifier="FB_ChoiceD" outcome-identifier="FEEDBACK">Incorrecto. Si el aumento fuera de 50 %, entonces las descargas adicionales serían <math xmlns="http://www.w3.org/1998/Math/MathML"><mrow><mn>1&#160;800&#160;000</mn><mo>×</mo><mfrac><mn>50</mn><mn>100</mn></mfrac><mo>=</mo><mn>1&#160;800&#160;000</mn><mo>×</mo><mn>0,5</mn><mo>=</mo><mn>900&#160;000</mn></mrow></math>. Pero el enunciado indica <math xmlns="http://www.w3.org/1998/Math/MathML"><mn>90&#160;000</mn></math> descargas adicionales, y <math xmlns="http://www.w3.org/1998/Math/MathML"><mn>900&#160;000</mn></math> no coincide con <math xmlns="http://www.w3.org/1998/Math/MathML"><mn>90&#160;000</mn></math>.</qti-feedback-inline></qti-simple-choice>
    </qti-choice-interaction>
    <qti-feedback-block identifier="show" outcome-identifier="SOLUTION" show-hide="show">
      <qti-content-body>
        <p><strong>Resolución paso a paso</strong></p>
        <ol>
          <li>
            <p><strong>Identificar qué se compara</strong></p>
            <p>El problema pide el porcentaje de aumento que representan las <strong>90 000</strong> descargas adicionales respecto de las <strong>1 800 000</strong> descargas del primer mes.</p>
          </li>
          <li>
            <p><strong>Plantear la razón</strong></p>
            <p>El porcentaje de aumento se obtiene con la razón:</p>
            <p><math xmlns="http://www.w3.org/1998/Math/MathML"><mrow><mfrac><mtext>descargas adicionales</mtext><mtext>descargas del primer mes</mtext></mfrac><mo>=</mo><mfrac><mn>90&#160;000</mn><mn>1&#160;800&#160;000</mn></mfrac></mrow></math></p>
          </li>
          <li>
            <p><strong>Simplificar la fracción</strong></p>
            <p><math xmlns="http://www.w3.org/1998/Math/MathML"><mrow><mfrac><mn>90&#160;000</mn><mn>1&#160;800&#160;000</mn></mfrac><mo>=</mo><mfrac><mn>9</mn><mn>180</mn></mfrac><mo>=</mo><mfrac><mn>1</mn><mn>20</mn></mfrac><mo>=</mo><mn>0,05</mn></mrow></math></p>
          </li>
          <li>
            <p><strong>Convertir a porcentaje</strong></p>
            <p><math xmlns="http://www.w3.org/1998/Math/MathML"><mrow><mn>0,05</mn><mo>×</mo><mn>100</mn><mo>=</mo><mn>5</mn></mrow></math></p>
            <p>Entonces, el aumento fue de <strong>5 %</strong>.</p>
          </li>
          <li>
            <p><strong>Conclusión</strong></p>
            <p>La alternativa correcta es <strong>B</strong>.</p>
          </li>
        </ol>
      </qti-content-body>
    </qti-feedback-block>
  </qti-item-body>
  <qti-response-processing>
    <qti-response-condition>
      <qti-response-if>
        <qti-match>
          <qti-variable identifier="RESPONSE"/>
          <qti-base-value base-type="identifier">ChoiceB</qti-base-value>
        </qti-match>
        <qti-set-outcome-value identifier="SCORE">
          <qti-base-value base-type="float">1</qti-base-value>
        </qti-set-outcome-value>
        <qti-set-outcome-value identifier="FEEDBACK">
          <qti-base-value base-type="identifier">FB_ChoiceB</qti-base-value>
        </qti-set-outcome-value>
        <qti-set-outcome-value identifier="SOLUTION">
          <qti-base-value base-type="identifier">show</qti-base-value>
        </qti-set-outcome-value>
      </qti-response-if>
      <qti-response-else-if>
        <qti-match>
          <qti-variable identifier="RESPONSE"/>
          <qti-base-value base-type="identifier">ChoiceA</qti-base-value>
        </qti-match>
        <qti-set-outcome-value identifier="FEEDBACK">
          <qti-base-value base-type="identifier">FB_ChoiceA</qti-base-value>
        </qti-set-outcome-value>
        <qti-set-outcome-value identifier="SOLUTION">
          <qti-base-value base-type="identifier">show</qti-base-value>
        </qti-set-outcome-value>
      </qti-response-else-if>
      <qti-response-else-if>
        <qti-match>
          <qti-variable identifier="RESPONSE"/>
          <qti-base-value base-type="identifier">ChoiceC</qti-base-value>
        </qti-match>
        <qti-set-outcome-value identifier="FEEDBACK">
          <qti-base-value base-type="identifier">FB_ChoiceC</qti-base-value>
        </qti-set-outcome-value>
        <qti-set-outcome-value identifier="SOLUTION">
          <qti-base-value base-type="identifier">show</qti-base-value>
        </qti-set-outcome-value>
      </qti-response-else-if>
      <qti-response-else-if>
        <qti-match>
          <qti-variable identifier="RESPONSE"/>
          <qti-base-value base-type="identifier">ChoiceD</qti-base-value>
        </qti-match>
        <qti-set-outcome-value identifier="FEEDBACK">
          <qti-base-value base-type="identifier">FB_ChoiceD</qti-base-value>
        </qti-set-outcome-value>
        <qti-set-outcome-value identifier="SOLUTION">
          <qti-base-value base-type="identifier">show</qti-base-value>
        </qti-set-outcome-value>
      </qti-response-else-if>
      <qti-response-else>
        <qti-set-outcome-value identifier="FEEDBACK">
          <qti-base-value base-type="identifier">FB_ChoiceA</qti-base-value>
        </qti-set-outcome-value>
        <qti-set-outcome-value identifier="SOLUTION">
          <qti-base-value base-type="identifier">show</qti-base-value>
        </qti-set-outcome-value>
      </qti-response-else>
    </qti-response-condition>
  </qti-response-processing>
</qti-assessment-item>