{
  "sections": [
    {
      "block_name": "objective",
      "index": null,
      "html": "<header data-block=\"objective\">\n  <h1>Mini-clase: Representación algebraica de áreas y perímetros</h1>\n  <p data-role=\"learning-objective\">Al terminar esta mini-clase podrás expresar con álgebra el área y el perímetro de cuadrados y rectángulos y plantear ecuaciones para hallar lados desconocidos.</p>\n  <p data-role=\"paes-relevance\">Lo usarás en ítems PAES sobre áreas y perímetros.</p>\n</header>",
      "word_count": 40,
      "validation_status": "pending",
      "validation_errors": []
    },
    {
      "block_name": "concept",
      "index": null,
      "html": "<section data-block=\"concept\" data-role=\"content\">\n  <header>\n    <h2>Área y perímetro con expresiones algebraicas</h2>\n  </header>\n  <h3>Área con variables</h3>\n  <p>El área mide cuánta superficie cubre la figura: para un rectángulo usa <math xmlns=\"http://www.w3.org/1998/Math/MathML\"><mrow><mi>A</mi><mo>=</mo><mi>l</mi><mo>&#x00D7;</mo><mi>a</mi></mrow></math> y para un cuadrado usa <math xmlns=\"http://www.w3.org/1998/Math/MathML\"><mrow><mi>A</mi><mo>=</mo><msup><mi>l</mi><mn>2</mn></msup></mrow></math>.</p>\n  <p>Si el largo y el ancho se describen con expresiones como <math xmlns=\"http://www.w3.org/1998/Math/MathML\"><mrow><mi>x</mi></mrow></math> y <math xmlns=\"http://www.w3.org/1998/Math/MathML\"><mrow><mi>x</mi><mo>+</mo><mn>2</mn></mrow></math>, escribe el área como producto: <math xmlns=\"http://www.w3.org/1998/Math/MathML\"><mrow><mi>A</mi><mo>=</mo><mi>x</mi><mo>(</mo><mi>x</mi><mo>+</mo><mn>2</mn><mo>)</mo></mrow></math>.</p>\n  <h3>Perímetro con variables</h3>\n  <p>El perímetro mide el contorno, la suma de todos los lados: en un rectángulo usa <math xmlns=\"http://www.w3.org/1998/Math/MathML\"><mrow><mi>P</mi><mo>=</mo><mn>2</mn><mi>l</mi><mo>+</mo><mn>2</mn><mi>a</mi></mrow></math> y en un cuadrado usa <math xmlns=\"http://www.w3.org/1998/Math/MathML\"><mrow><mi>P</mi><mo>=</mo><mn>4</mn><mi>l</mi></mrow></math>.</p>\n  <p>Si el largo es <math xmlns=\"http://www.w3.org/1998/Math/MathML\"><mrow><mi>x</mi></mrow></math> y el ancho es <math xmlns=\"http://www.w3.org/1998/Math/MathML\"><mrow><mi>x</mi><mo>+</mo><mn>3</mn></mrow></math>, modela el perímetro como <math xmlns=\"http://www.w3.org/1998/Math/MathML\"><mrow><mi>P</mi><mo>=</mo><mn>2</mn><mi>x</mi><mo>+</mo><mn>2</mn><mo>(</mo><mi>x</mi><mo>+</mo><mn>3</mn><mo>)</mo></mrow></math>.</p>\n  <h3>Trampa PAES</h3>\n  <p>❌ Al hablar de \"cubrir\" una pista con lados <math xmlns=\"http://www.w3.org/1998/Math/MathML\"><mrow><mi>x</mi></mrow></math> y <math xmlns=\"http://www.w3.org/1998/Math/MathML\"><mrow><mi>x</mi><mo>+</mo><mn>4</mn></mrow></math>, muchos escriben el perímetro <math xmlns=\"http://www.w3.org/1998/Math/MathML\"><mrow><mi>P</mi><mo>=</mo><mn>2</mn><mi>x</mi><mo>+</mo><mn>2</mn><mo>(</mo><mi>x</mi><mo>+</mo><mn>4</mn><mo>)</mo></mrow></math>.</p>\n  <p>✔ Si el enunciado habla de superficie, usa área como producto <math xmlns=\"http://www.w3.org/1998/Math/MathML\"><mrow><mi>A</mi><mo>=</mo><mi>x</mi><mo>(</mo><mi>x</mi><mo>+</mo><mn>4</mn><mo>)</mo></mrow></math>; si habla de bordear o cercar, usa la suma de lados para el perímetro.</p>\n</section>",
      "word_count": 170,
      "validation_status": "pending",
      "validation_errors": []
    },
    {
      "block_name": "worked-example",
      "index": 1,
      "html": "<section data-block=\"worked-example\" data-index=\"1\">\n  <header>\n    <h2>Ejemplo resuelto</h2>\n    <p>Un marco rectangular tiene largo <math xmlns=\"http://www.w3.org/1998/Math/MathML\"><mrow><mi>x</mi><mo>+</mo><mn>3</mn></mrow></math> cm y ancho <math xmlns=\"http://www.w3.org/1998/Math/MathML\"><mrow><mi>x</mi><mo>+</mo><mn>1</mn></mrow></math> cm. Su perímetro es <math xmlns=\"http://www.w3.org/1998/Math/MathML\"><mrow><mn>40</mn></mrow></math> cm. Escribe el área en función de <math xmlns=\"http://www.w3.org/1998/Math/MathML\"><mrow><mi>x</mi></mrow></math> y usa el perímetro para hallar <math xmlns=\"http://www.w3.org/1998/Math/MathML\"><mrow><mi>x</mi></mrow></math>.</p>\n  </header>\n  <ol data-role=\"steps\">\n    <li><details>\n      <summary><strong>Paso 1:</strong> Identifica si necesitas área o perímetro y extrae largo y ancho del enunciado.</summary>\n      <p>“Marco” indica borde, así que trabajas con perímetro, y la frase “largo <math xmlns=\"http://www.w3.org/1998/Math/MathML\"><mrow><mi>x</mi><mo>+</mo><mn>3</mn></mrow></math>” y “ancho <math xmlns=\"http://www.w3.org/1998/Math/MathML\"><mrow><mi>x</mi><mo>+</mo><mn>1</mn></mrow></math>” te da directamente ambas dimensiones del rectángulo.</p>\n      <p>Muchos confunden área con perímetro; aquí no hablan de cubrir superficie, sino de rodear el marco.</p>\n    </details></li>\n    <li><details>\n      <summary><strong>Paso 2:</strong> Escribe largo y ancho como expresiones algebraicas (monomios o binomios en una variable).</summary>\n      <p>Escribe largo <math xmlns=\"http://www.w3.org/1998/Math/MathML\"><mrow><mi>L</mi><mo>=</mo><mi>x</mi><mo>+</mo><mn>3</mn></mrow></math> y ancho <math xmlns=\"http://www.w3.org/1998/Math/MathML\"><mrow><mi>A</mi><mo>=</mo><mi>x</mi><mo>+</mo><mn>1</mn></mrow></math> en forma algebraica.</p>\n      <p>Así traduces correctamente “3 más que <math xmlns=\"http://www.w3.org/1998/Math/MathML\"><mrow><mi>x</mi></mrow></math>” y “1 más que <math xmlns=\"http://www.w3.org/1998/Math/MathML\"><mrow><mi>x</mi></mrow></math>”, evitando cambiar el signo o el orden.</p>\n    </details></li>\n    <li><details>\n      <summary><strong>Paso 3:</strong> Modela área o perímetro usando la fórmula correcta y, si hace falta, simplifica la expresión.</summary>\n      <p>Área: <math xmlns=\"http://www.w3.org/1998/Math/MathML\"><mrow><mi>A</mi><mo>(</mo><mi>x</mi><mo>)</mo><mo>=</mo><mo>(</mo><mi>x</mi><mo>+</mo><mn>3</mn><mo>)</mo><mo>(</mo><mi>x</mi><mo>+</mo><mn>1</mn><mo>)</mo></mrow></math>; si multiplicas correctamente cada término obtienes <math xmlns=\"http://www.w3.org/1998/Math/MathML\"><mrow><msup><mi>x</mi><mn>2</mn></msup><mo>+</mo><mn>4</mn><mi>x</mi><mo>+</mo><mn>3</mn></mrow></math>.</p>\n      <p>Perímetro: suma los cuatro lados <math xmlns=\"http://www.w3.org/1998/Math/MathML\"><mrow><mi>P</mi><mo>(</mo><mi>x</mi><mo>)</mo><mo>=</mo><mo>(</mo><mi>x</mi><mo>+</mo><mn>3</mn><mo>)</mo><mo>+</mo><mo>(</mo><mi>x</mi><mo>+</mo><mn>3</mn><mo>)</mo><mo>+</mo><mo>(</mo><mi>x</mi><mo>+</mo><mn>1</mn><mo>)</mo><mo>+</mo><mo>(</mo><mi>x</mi><mo>+</mo><mn>1</mn><mo>)</mo></mrow></math>, que se agrupa como <math xmlns=\"http://www.w3.org/1998/Math/MathML\"><mrow><mn>2</mn><mo>(</mo><mi>x</mi><mo>+</mo><mn>3</mn><mo>)</mo><mo>+</mo><mn>2</mn><mo>(</mo><mi>x</mi><mo>+</mo><mn>1</mn><mo>)</mo></mrow></math> y luego <math xmlns=\"http://www.w3.org/1998/Math/MathML\"><mrow><mn>4</mn><mi>x</mi><mo>+</mo><mn>8</mn></mrow></math>, sin olvidar el factor <math xmlns=\"http://www.w3.org/1998/Math/MathML\"><mrow><mn>2</mn></mrow></math> en cada par de lados.</p>\n    </details></li>\n    <li><details>\n      <summary><strong>Paso 4:</strong> Si te dan un valor de área o perímetro, iguala tu expresión a ese dato y resuelve la ecuación para hallar la dimensión desconocida.</summary>\n      <p>Iguala la expresión del perímetro al dato: <math xmlns=\"http://www.w3.org/1998/Math/MathML\"><mrow><mn>4</mn><mi>x</mi><mo>+</mo><mn>8</mn><mo>=</mo><mn>40</mn></mrow></math>, porque <math xmlns=\"http://www.w3.org/1998/Math/MathML\"><mrow><mn>40</mn></mrow></math> representa todo el borde, no un solo lado.</p>\n      <p>Resuelve: <math xmlns=\"http://www.w3.org/1998/Math/MathML\"><mrow><mn>4</mn><mi>x</mi><mo>=</mo><mn>32</mn></mrow></math>, luego <math xmlns=\"http://www.w3.org/1998/Math/MathML\"><mrow><mi>x</mi><mo>=</mo><mn>8</mn></mrow></math>; verifica sustituyendo en el perímetro: lados <math xmlns=\"http://www.w3.org/1998/Math/MathML\"><mrow><mn>11</mn></mrow></math> y <math xmlns=\"http://www.w3.org/1998/Math/MathML\"><mrow><mn>9</mn></mrow></math> dan <math xmlns=\"http://www.w3.org/1998/Math/MathML\"><mrow><mn>11</mn><mo>+</mo><mn>11</mn><mo>+</mo><mn>9</mn><mo>+</mo><mn>9</mn><mo>=</mo><mn>40</mn></mrow></math>, así confirmas la ecuación.</p>\n    </details></li>\n  </ol>\n  <p data-role=\"micro-reinforcement\">Si obtuviste <math xmlns=\"http://www.w3.org/1998/Math/MathML\"><mrow><mi>x</mi><mo>=</mo><mn>8</mn></mrow></math>, vas bien — el punto clave fue escribir <math xmlns=\"http://www.w3.org/1998/Math/MathML\"><mrow><mi>P</mi><mo>(</mo><mi>x</mi><mo>)</mo><mo>=</mo><mn>2</mn><mo>(</mo><mi>x</mi><mo>+</mo><mn>3</mn><mo>)</mo><mo>+</mo><mn>2</mn><mo>(</mo><mi>x</mi><mo>+</mo><mn>1</mn><mo>)</mo></mrow></math> y luego igualarlo a <math xmlns=\"http://www.w3.org/1998/Math/MathML\"><mrow><mn>40</mn></mrow></math>.</p>\n  <ul data-role=\"paes-checklist\">\n    <li>✅ ¿Usaste producto de lados para área y suma de lados (con factor 2) para perímetro?</li>\n    <li>✅ ¿Escribiste bien largo y ancho en álgebra según las frases del enunciado (más que, menos que)?</li>\n    <li>✅ Si te dieron un área o perímetro numérico, ¿lo igualaste a tu expresión para formar la ecuación correcta?</li>\n  </ul>\n</section>",
      "word_count": 380,
      "validation_status": "pending",
      "validation_errors": []
    }
  ]
}